destral/__init__.py
destral/cli.py
destral/cover.py
destral/junitxml_testing.py
destral/linter.py
destral/openerp.py
destral/patch.py
destral/testing.py
destral/transaction.py
destral/utils.py
spec/__init__.py
spec/patch_spec.py
spec/testing_spec.py
spec/utils_spec.py
spec/fixtures/__init__.py
destral-2.3.0.dist-info/METADATA
destral-2.3.0.dist-info/WHEEL
destral-2.3.0.dist-info/entry_points.txt
destral-2.3.0.dist-info/top_level.txt
destral-2.3.0.dist-info/RECORD
