Metadata-Version: 2.1
Name: destral
Version: 2.3.0
Summary: OpenERP testing framework
Home-page: https://github.com/gisce/destral
Author: GISCE-TI, S.L.
Author-email: devel@gisce.net
License: GNU GPLv3
Platform: UNKNOWN
Requires-Dist: requests
Requires-Dist: osconf
Requires-Dist: expects
Requires-Dist: six
Requires-Dist: click
Requires-Dist: coverage
Requires-Dist: lazy-object-proxy (<1.7.0)
Requires-Dist: pylint (<=2.17.7)
Requires-Dist: python-dateutil
Requires-Dist: babel (>=2.4.0)
Requires-Dist: junit-xml
Requires-Dist: psycopg2
Requires-Dist: mock
Requires-Dist: xlrd (==1.2.0)
Requires-Dist: mamba (<0.11.0)
Requires-Dist: typing (==3.10.0.0) ; python_version < "3.0"
